coreason_synthesis/__init__.py
coreason_synthesis/analyzer.py
coreason_synthesis/appraiser.py
coreason_synthesis/clients/__init__.py
coreason_synthesis/clients/foundry.py
coreason_synthesis/clients/mcp.py
coreason_synthesis/clients/openai.py
coreason_synthesis/compositor.py
coreason_synthesis/extractor.py
coreason_synthesis/forager.py
coreason_synthesis/interfaces.py
coreason_synthesis/mocks/__init__.py
coreason_synthesis/mocks/embedding.py
coreason_synthesis/mocks/mcp.py
coreason_synthesis/mocks/teacher.py
coreason_synthesis/models.py
coreason_synthesis/perturbator.py
coreason_synthesis/pipeline.py
coreason_synthesis/py.typed
coreason_synthesis/server.py
coreason_synthesis/utils/__init__.py
coreason_synthesis/utils/http.py
coreason_synthesis/utils/logger.py
coreason_synthesis-0.3.0.dist-info/METADATA
coreason_synthesis-0.3.0.dist-info/WHEEL
coreason_synthesis-0.3.0.dist-info/licenses/LICENSE
coreason_synthesis-0.3.0.dist-info/licenses/NOTICE
coreason_synthesis-0.3.0.dist-info/RECORD
