Metadata-Version: 2.4
Name: coreason_synthesis
Version: 0.3.0
Summary: A new Python project.
License: # The Prosperity Public License 3.0.0
License-File: LICENSE
License-File: NOTICE
Author: Gowtham A Rao
Author-email: gowtham.rao@coreason.ai
Requires-Python: >=3.11
Classifier: License :: Other/Proprietary License
Classifier: Programming Language :: Python :: 3.12
Classifier: Operating System :: OS Independent
Requires-Dist: aiofiles (>=25.1.0,<26.0.0)
Requires-Dist: anyio (>=4.12.1,<5.0.0)
Requires-Dist: coreason-identity
Requires-Dist: fastapi (>=0.111.0,<0.112.0)
Requires-Dist: httpx (>=0.28.1,<0.29.0)
Requires-Dist: loguru (>=0.7.2,<0.8.0)
Requires-Dist: numpy (>=2.4.1,<3.0.0)
Requires-Dist: pydantic (>=2.12.5,<3.0.0)
Requires-Dist: requests (>=2.32.5,<3.0.0)
Requires-Dist: uvicorn[standard] (>=0.30.0,<0.31.0)
Project-URL: Documentation, https://github.com/CoReason-AI/coreason_synthesis
Project-URL: Homepage, https://github.com/CoReason-AI/coreason_synthesis
Project-URL: Repository, https://github.com/CoReason-AI/coreason_synthesis
